data_flow_modelling/and22.v
module and22(input [1:0]a, input [1:0]b, output [1:0]z );
assign z[0] = a[0] & b[0];
assign z[1] = a[1] & b[1];
endmodule

data_flow_modelling/and22_tb.v
`timescale 1ns / 1ns
`include "and22.v"

module and22_tb;

reg [1:0] a,b;
wire [1:0]z;

and22 uut (a,b,z);

initial begin
    $dumpfile("and22_tb.vcd");
    $dumpvars(0, and22_tb);
    {a, b} = 4'd0; #10;
    {a, b} = 4'd1; #10;
    {a, b} = 4'd2; #10;
    {a, b} = 4'd3; #10;
    {a, b} = 4'd4; #10;
    {a, b} = 4'd5; #10;
    {a, b} = 4'd6; #10;
    {a, b} = 4'd7; #10;
    {a, b} = 4'd8; #10;
    {a, b} = 4'd9; #10;
    {a, b} = 4'd10; #10;
    {a, b} = 4'd11; #10;
    {a, b} = 4'd12; #10;
    {a, b} = 4'd13; #10;
    {a, b} = 4'd14; #10;
    {a, b} = 4'd15; #10;
    
end

endmodule

data_flow_modelling/and22_tb.vcd
$date
	Sun Jan 23 21:55:59 2022
$end
$version
	Icarus Verilog
$end
$timescale
	1ns
$end
$scope module and22_tb $end
$var wire 2 ! z [1:0] $end
$var reg 2 " a [1:0] $end
$var reg 2 # b [1:0] $end
$scope module uut $end
$var wire 2 $ a [1:0] $end
$var wire 2 % b [1:0] $end
$var wire 2 & z [1:0] $end
$upscope $end
$upscope $end
$enddefinitions $end
#0
$dumpvars
b0 &
b0 %
b0 $
b0 #
b0 "
b0 !
$end
#10
b1 #
b1 %
#20
b10 #
b10 %
#30
b11 #
b11 %
#40
b1 "
b1 $
b0 #
b0 %
#50
b1 !
b1 &
b1 #
b1 %
#60
b0 !
b0 &
b10 #
b10 %
#70
b1 !
b1 &
b11 #
b11 %
#80
b0 !
b0 &
b10 "
b10 $
b0 #
b0 %
#90
b1 #
b1 %
#100
b10 !
b10 &
b10 #
b10 %
#110
b11 #
b11 %
#120
b0 !
b0 &
b11 "
b11 $
b0 #
b0 %
#130
b1 !
b1 &
b1 #
b1 %
#140
b10 !
b10 &
b10 #
b10 %
#150
b11 !
b11 &
b11 #
b11 %
