data_flow_modelling/fulladdr2.v
module fulladdr2(input a, input b, input ci, output s, output c);
assign s = (a^b)^ci;
assign c = a&b | b&ci | a&ci;
endmodule

data_flow_modelling/fulladdr2_tb.v
`timescale 1ns / 1ns
`include "fulladdr2.v"

module fulladdr2_tb();
reg a, b, ci;
wire s,c;

fulladdr2 uut (a,b,ci,s,c);
initial begin
    $dumpfile("fulladdr2_tb.vcd");
    $dumpvars(0,fulladdr2_tb);
    {a,b,ci} = 3'd0;#10;
    {a,b,ci} = 3'd1;#10;
    {a,b,ci} = 3'd2;#10;
    {a,b,ci} = 3'd3;#10;
    {a,b,ci} = 3'd4;#10;
    {a,b,ci} = 3'd5;#10;
    {a,b,ci} = 3'd6;#10;
    {a,b,ci} = 3'd7;#10;
    $display("This is complete");
end

endmodule

data_flow_modelling/fulladdr2_tb.vcd
$date
	Sun Jan 23 23:10:04 2022
$end
$version
	Icarus Verilog
$end
$timescale
	1ns
$end
$scope module fulladdr2_tb $end
$var wire 1 ! s $end
$var wire 1 " c $end
$var reg 1 # a $end
$var reg 1 $ b $end
$var reg 1 % ci $end
$scope module uut $end
$var wire 1 # a $end
$var wire 1 $ b $end
$var wire 1 " c $end
$var wire 1 % ci $end
$var wire 1 ! s $end
$upscope $end
$upscope $end
$enddefinitions $end
#0
$dumpvars
0%
0$
0#
0"
0!
$end
#10
1!
1%
#20
1!
1$
0%
#30
1"
0!
1%
#40
0"
1!
1#
0$
0%
#50
1"
0!
1%
#60
1"
0!
1$
0%
#70
1!
1%
