gate_level_modelling/mux21.v
module and_gate(output a, input b,c);
assign a = b&c;
endmodule
module or_gate (output l, input m,n);
assign l = m|n;
endmodule
module not_gate(output d, input e);
assign d = ~e;
endmodule

module m21(input d0,d1,s, output y);
wire t1,t2,t3;
and_gate u1(t1,d1,s);
not_gate u2(t2,s);
and_gate u3(t3,d0,t2);
or_gate u4(y,t1,t3);
endmodule

gate_level_modelling/mux2_tb.v
`timescale 1ns/1ns
`include "mux21.v"
module mux2_tb;
reg d0,d1,s;
wire y;
m21 name (.y(y), .d0(d0), .d1(d1), .s(s));
initial begin
    $dumpfile("m21_tb.vcd");
    $dumpvars;
    d0=0;d1=0;s=0; #100
    $finish;
end
always #40 d0=~d0;
always #20 d1=~d1;
always #10 s=~s;

endmodule

gate_level_modelling/m21_tb.vcd
$date
	Tue Jan 25 22:38:13 2022
$end
$version
	Icarus Verilog
$end
$timescale
	1ns
$end
$scope module mux2_tb $end
$var wire 1 ! y $end
$var reg 1 " d0 $end
$var reg 1 # d1 $end
$var reg 1 $ s $end
$scope module name $end
$var wire 1 " d0 $end
$var wire 1 # d1 $end
$var wire 1 $ s $end
$var wire 1 ! y $end
$var wire 1 % t3 $end
$var wire 1 & t2 $end
$var wire 1 ' t1 $end
$scope module u1 $end
$var wire 1 ' a $end
$var wire 1 # b $end
$var wire 1 $ c $end
$upscope $end
$scope module u2 $end
$var wire 1 & d $end
$var wire 1 $ e $end
$upscope $end
$scope module u3 $end
$var wire 1 % a $end
$var wire 1 " b $end
$var wire 1 & c $end
$upscope $end
$scope module u4 $end
$var wire 1 ! l $end
$var wire 1 ' m $end
$var wire 1 % n $end
$upscope $end
$upscope $end
$upscope $end
$enddefinitions $end
#0
$dumpvars
0'
1&
0%
0$
0#
0"
0!
$end
#10
0&
1$
#20
1&
0$
1#
#30
1!
1'
0&
1$
#40
1%
1!
1&
0'
0$
0#
1"
#50
0!
0%
0&
1$
#60
1!
1%
1&
0$
1#
#70
0%
1'
0&
1$
#80
0!
1&
0'
0$
0#
0"
#90
0&
1$
#100
1&
0$
1#
