gate_level_modelling/mux4.v
module and_gate(output a, input c,d,e);
and(a,c,d,e);
endmodule

module not_gate(output w, input y);
not(w,y);
endmodule

module or_gate(output t, input f,g,h,i);
or (t,f,g,h,i);
endmodule

module m41(input s0,s1,d0,d1,d2,d3, output F);
wire t1,t2,t3,t4,t5,t6;
and_gate u1(t1, d3,s0,s1);
not_gate u2(t2, s1); //s1 bar at t2
and_gate u3(t3, t2,d2,s0);
not_gate u4(t4, s0); //s0 bar at t4
and_gate u5(t5, d1,s1,t4);
and_gate u6(t6, d0,t4,t2);
or_gate u7(F, t6,t5,t3,t1);
endmodule

gate_level_modelling/mux4_tb.v
`timescale 1ns/1ns
`include "mux4.v"
module mux4_tb;
reg d0,d1,d2,d3,s0,s1;
wire f;
m41 name (.F(f), .d0(d0), .d1(d1), .d2(d2), .d3(d3), .s0(s0), .s1(s1));
initial begin
    $dumpfile("mux4_tb.vcd");
    $dumpvars;
    d0=0;d1=0;d2=0;d3=0;s0=0;s1=0; 
    #160 $finish;
end
always #80 d0=~d0;
always #40 d1=~d1;
always #20 d2=~d2;
always #10 d3=~d3;
always #10 s0=~s0;
always #5 s1=~s1;
endmodule

gate_level_modelling/mux4_tb.vcd
$date
	Tue Jan 25 23:12:27 2022
$end
$version
	Icarus Verilog
$end
$timescale
	1ns
$end
$scope module mux4_tb $end
$var wire 1 ! f $end
$var reg 1 " d0 $end
$var reg 1 # d1 $end
$var reg 1 $ d2 $end
$var reg 1 % d3 $end
$var reg 1 & s0 $end
$var reg 1 ' s1 $end
$scope module name $end
$var wire 1 " d0 $end
$var wire 1 # d1 $end
$var wire 1 $ d2 $end
$var wire 1 % d3 $end
$var wire 1 & s0 $end
$var wire 1 ' s1 $end
$var wire 1 ( t6 $end
$var wire 1 ) t5 $end
$var wire 1 * t4 $end
$var wire 1 + t3 $end
$var wire 1 , t2 $end
$var wire 1 - t1 $end
$var wire 1 ! F $end
$scope module u1 $end
$var wire 1 - a $end
$var wire 1 % c $end
$var wire 1 & d $end
$var wire 1 ' e $end
$upscope $end
$scope module u2 $end
$var wire 1 , w $end
$var wire 1 ' y $end
$upscope $end
$scope module u3 $end
$var wire 1 + a $end
$var wire 1 , c $end
$var wire 1 $ d $end
$var wire 1 & e $end
$upscope $end
$scope module u4 $end
$var wire 1 * w $end
$var wire 1 & y $end
$upscope $end
$scope module u5 $end
$var wire 1 ) a $end
$var wire 1 # c $end
$var wire 1 ' d $end
$var wire 1 * e $end
$upscope $end
$scope module u6 $end
$var wire 1 ( a $end
$var wire 1 " c $end
$var wire 1 * d $end
$var wire 1 , e $end
$upscope $end
$scope module u7 $end
$var wire 1 ( f $end
$var wire 1 ) g $end
$var wire 1 + h $end
$var wire 1 - i $end
$var wire 1 ! t $end
$upscope $end
$upscope $end
$upscope $end
$enddefinitions $end
#0
$dumpvars
0-
1,
0+
1*
0)
0(
0'
0&
0%
0$
0#
0"
0!
$end
#5
0,
1'
#10
1,
0*
0'
1&
1%
#15
1!
1-
0,
1'
#20
0!
1,
1*
0-
0'
0&
0%
1$
#25
0,
1'
#30
1!
1+
1,
0*
0'
1&
1%
#35
0+
1-
0,
1'
#40
0!
1,
1*
0-
0'
0&
0%
0$
1#
#45
1!
0,
1)
1'
#50
0!
1,
0)
0*
0'
1&
1%
#55
1!
1-
0,
1'
#60
0!
1,
1*
0-
0'
0&
0%
1$
#65
1!
0,
1)
1'
#70
1+
1!
1,
0)
0*
0'
1&
1%
#75
0+
1-
0,
1'
#80
1(
1!
1,
1*
0-
0'
0&
0%
0$
0#
1"
#85
0!
0(
0,
1'
#90
1,
0*
0'
1&
1%
#95
1!
1-
0,
1'
#100
1(
1!
1,
1*
0-
0'
0&
0%
1$
#105
0!
0(
0,
1'
#110
1!
1+
1,
0*
0'
1&
1%
#115
0+
1-
0,
1'
#120
1(
1!
1,
1*
0-
0'
0&
0%
0$
1#
#125
0(
0,
1)
1'
#130
0!
1,
0)
0*
0'
1&
1%
#135
1!
1-
0,
1'
#140
1(
1!
1,
1*
0-
0'
0&
0%
1$
#145
0(
0,
1)
1'
#150
1+
1!
1,
0)
0*
0'
1&
1%
#155
0+
1-
0,
1'
#160
0!
1,
1*
0-
0'
0&
0%
0$
0#
0"
