gate_level_modelling/mux8.v
module mux8(input D0, D1, D2, D3, D4, D5, D6, D7,
input s0,s1,s2,
output F);
wire [11:0]t;

not(t[0], s0); //t0 not of s0
not(t[1], s1); //t1 not of s1
not(t[2], s2); //t2 not of s2

and(t[4], t[0], t[1], t[2], D0);
and(t[5], t[0], t[1], s2, D1);
and(t[6], t[0], s1, t[2], D2);
and(t[7], t[0], s1, s2, D3);
and(t[8], s0, t[1], t[2], D4);
and(t[9], s0, t[1], s2, D5);
and(t[10], s0, s1, t[2], D6);
and(t[11], s0, s1, s2, D7);

or(F, t[4], t[5], t[6], t[7], t[8], t[9], t[10], t[11]);

endmodule

gate_level_modelling/mux8_tb.v
`timescale 1ns/1ns
`include "mux8.v"

module mux8_tb;
reg D0, D1, D2, D3, D4, D5, D6, D7;
reg s0,s1,s2;
wire pp;
mux8 name (.F(pp), .D0(D0),  .D1(D1), .D2(D2), .D3(D3), .D4(D4), .D5(D5), .D6(D6), .D7(D7), .s0(s0),  .s1(s1),  .s2(s2));
initial begin
    $dumpfile("mux8_tb.vcd");
    $dumpvars(0,mux8_tb);
    D0=0;D1=0;D2=0;D3=0;D4=0;D5=0;D6=0;D7=0;s0=0;s1=0;s2=0;
    #500 $finish;
end
always #1 D0=~D0;
always #2 D1=~D1;
always #3 D2=~D2;
always #4 D3=~D3;
always #5 D4=~D4;
always #6 D5=~D5;
always #7 D6=~D6;
always #8 D7=~D7;
always #9 s0=~s0;
always #10 s1=~s1;
always #11 s2=~s2;
endmodule

gate_level_modelling/mux8_tb.vcd
$date
	Wed Jan 26 22:05:13 2022
$end
$version
	Icarus Verilog
$end
$timescale
	1ns
$end
$scope module mux8_tb $end
$var wire 1 ! pp $end
$var reg 1 " D0 $end
$var reg 1 # D1 $end
$var reg 1 $ D2 $end
$var reg 1 % D3 $end
$var reg 1 & D4 $end
$var reg 1 ' D5 $end
$var reg 1 ( D6 $end
$var reg 1 ) D7 $end
$var reg 1 * s0 $end
$var reg 1 + s1 $end
$var reg 1 , s2 $end
$scope module name $end
$var wire 1 " D0 $end
$var wire 1 # D1 $end
$var wire 1 $ D2 $end
$var wire 1 % D3 $end
$var wire 1 & D4 $end
$var wire 1 ' D5 $end
$var wire 1 ( D6 $end
$var wire 1 ) D7 $end
$var wire 1 ! F $end
$var wire 1 * s0 $end
$var wire 1 + s1 $end
$var wire 1 , s2 $end
$var wire 12 - t [11:0] $end
$upscope $end
$upscope $end
$enddefinitions $end
#0
$dumpvars
b0z111 -
0,
0+
0*
0)
0(
0'
0&
0%
0$
0#
0"
0!
$end
#1
1!
b1z111 -
1"
#2
0!
b0z111 -
0"
1#
#3
1!
b1z111 -
1"
1$
#4
0!
b0z111 -
0"
0#
1%
#5
1!
b1z111 -
1"
1&
#6
0!
b0z111 -
0"
1#
0$
1'
#7
1!
b1z111 -
1"
1(
#8
0!
b0z111 -
0"
0#
0%
1)
#9
1!
b10000z110 -
1"
1$
1*
#10
b1000000z100 -
0"
1#
0&
1+
#11
b10000000z000 -
1"
1,
#12
0"
0#
0$
1%
0'
#13
1"
#14
0"
1#
0(
#15
1"
1$
1&
#16
0!
b0z000 -
0"
0#
0%
0)
#17
1"
#18
b0z001 -
0"
1#
0$
1'
0*
#19
1"
#20
b0z011 -
0"
0#
1%
0&
0+
#21
1"
1$
1(
#22
b0z111 -
0"
1#
0,
#23
1!
b1z111 -
1"
#24
0!
b0z111 -
0"
0#
0$
0%
0'
1)
#25
1!
b1z111 -
1"
1&
#26
0!
b0z111 -
0"
1#
#27
1!
b10000z110 -
1"
1$
1*
#28
0"
0#
1%
0(
#29
1"
#30
0!
b0z100 -
0"
1#
0$
0&
1'
1+
#31
1"
#32
0"
0#
0%
0)
#33
b0z000 -
1"
1$
1,
#34
0"
1#
#35
1"
1&
1(
#36
1!
b1000z001 -
0"
0#
0$
1%
0'
0*
#37
1"
#38
0"
1#
#39
1"
1$
#40
0!
b0z011 -
0"
0#
0%
0&
1)
0+
#41
1"
#42
1!
b10z011 -
0"
1#
0$
1'
0(
#43
1"
#44
0!
b0z111 -
0"
0#
1%
0,
#45
1!
b10000z110 -
1"
1$
1&
1*
#46
0"
1#
#47
1"
#48
0"
0#
0$
0%
0'
0)
#49
1"
1(
#50
b1000000z100 -
0"
1#
0&
1+
#51
1"
1$
#52
0"
0#
1%
#53
1"
#54
0!
b0z101 -
0"
1#
0$
1'
0*
#55
1!
b1000z001 -
1"
1&
1,
#56
0!
b0z001 -
0"
0#
0%
0(
1)
#57
1"
1$
#58
0"
1#
#59
1"
#60
b0z011 -
0"
0#
0$
1%
0&
0'
0+
#61
1"
#62
1!
b10z011 -
0"
1#
#63
0!
b0z010 -
1"
1$
1(
1*
#64
0"
0#
0%
0)
#65
1"
1&
#66
1!
b10000z110 -
0"
1#
0$
1'
0,
#67
1"
#68
0"
0#
1%
#69
1"
1$
#70
0!
b0z100 -
0"
1#
0&
0(
1+
#71
1"
#72
b0z101 -
0"
0#
0$
0%
0'
1)
0*
#73
1"
#74
0"
1#
#75
1!
b100z101 -
1"
1$
1&
#76
0"
0#
1%
#77
b1000z001 -
1"
1(
1,
#78
0"
1#
0$
1'
#79
1"
#80
0!
b0z011 -
0"
0#
0%
0&
0)
0+
#81
1!
b100000z010 -
1"
1$
1*
#82
0"
1#
#83
1"
#84
0!
b0z010 -
0"
0#
0$
1%
0'
0(
#85
1"
1&
#86
0"
1#
#87
1"
1$
#88
1!
b10000z110 -
0"
0#
0%
1)
0,
#89
1"
#90
0!
b0z101 -
0"
1#
0$
0&
1'
0*
1+
#91
1"
1(
#92
0"
0#
1%
#93
1!
b100z101 -
1"
1$
#94
0"
1#
#95
1"
1&
#96
0!
b0z101 -
0"
0#
0$
0%
0'
0)
#97
1"
#98
0"
1#
0(
#99
0!
b0z000 -
1"
1$
1*
1,
#100
b0z010 -
0"
0#
1%
0&
0+
#101
1"
#102
1!
b100000z010 -
0"
1#
0$
1'
#103
1"
#104
0"
0#
0%
1)
#105
1"
1$
1&
1(
#106
0"
1#
#107
1"
#108
0!
b0z011 -
0"
0#
0$
1%
0'
0*
#109
1"
#110
b0z101 -
0"
1#
0&
1+
0,
#111
1!
b100z101 -
1"
1$
#112
0"
0#
0%
0(
0)
#113
1"
#114
0!
b0z101 -
0"
1#
0$
1'
#115
1"
1&
#116
0"
0#
1%
#117
0!
b0z100 -
1"
1$
1*
#118
0"
1#
#119
1!
b1000000z100 -
1"
1(
#120
0!
b0z110 -
0"
0#
0$
0%
0&
0'
1)
0+
#121
b0z010 -
1"
1,
#122
0"
1#
#123
1"
1$
#124
0"
0#
1%
#125
1"
1&
#126
1!
b10z011 -
0"
1#
0$
1'
0(
0*
#127
1"
#128
0!
b0z011 -
0"
0#
0%
0)
#129
1"
1$
#130
0!
b0z001 -
0"
1#
0&
1+
#131
1"
#132
b0z101 -
0"
0#
0$
1%
0'
0,
#133
1"
1(
#134
0"
1#
#135
1!
b1000000z100 -
1"
1$
1&
1*
#136
0"
0#
0%
1)
#137
1"
#138
0"
1#
0$
1'
#139
1"
#140
0!
b0z110 -
0"
0#
1%
0&
0(
0+
#141
1"
1$
#142
0"
1#
#143
1!
b100000z010 -
1"
1,
#144
0!
b0z011 -
0"
0#
0$
0%
0'
0)
0*
#145
1"
1&
#146
1!
b10z011 -
0"
1#
#147
1"
1$
1(
#148
0!
b0z011 -
0"
0#
1%
#149
1"
#150
1!
b1000z001 -
0"
1#
0$
0&
1'
1+
#151
1"
#152
0!
b0z001 -
0"
0#
0%
1)
#153
1!
b10000000z000 -
1"
1$
1*
#154
0!
b0z100 -
0"
1#
0(
0,
#155
1"
1&
#156
0"
0#
0$
1%
0'
#157
1"
#158
0"
1#
#159
1"
1$
#160
b0z110 -
0"
0#
0%
0&
0)
0+
#161
1"
1(
#162
b0z111 -
0"
1#
0$
1'
0*
#163
1!
b1z111 -
1"
#164
0!
b0z111 -
0"
0#
1%
#165
0!
b0z011 -
1"
1$
1&
1,
#166
1!
b10z011 -
0"
1#
#167
1"
#168
0!
b0z011 -
0"
0#
0$
0%
0'
0(
1)
#169
1"
#170
0!
b0z001 -
0"
1#
0&
1+
#171
1!
b10000000z000 -
1"
1$
1*
#172
0"
0#
1%
#173
1"
#174
0"
1#
0$
1'
#175
1"
1&
1(
#176
1!
b1000000z100 -
0"
0#
0%
0)
0,
#177
1"
1$
#178
0"
1#
#179
1"
#180
0!
b0z111 -
0"
0#
0$
1%
0&
0'
0*
0+
#181
1!
b1z111 -
1"
#182
0!
b0z111 -
0"
1#
0(
#183
1!
b1z111 -
1"
1$
#184
0!
b0z111 -
0"
0#
0%
1)
#185
1!
b1z111 -
1"
1&
#186
0!
b0z111 -
0"
1#
0$
1'
#187
1!
b10z011 -
1"
1,
#188
0!
b0z011 -
0"
0#
1%
#189
1!
b100000z010 -
1"
1$
1(
1*
#190
b10000000z000 -
0"
1#
0&
1+
#191
1"
#192
0!
b0z000 -
0"
0#
0$
0%
0'
0)
#193
1"
#194
0"
1#
#195
1"
1$
1&
#196
0"
0#
1%
0(
#197
1"
#198
b0z101 -
0"
1#
0$
1'
0*
0,
#199
1"
#200
b0z111 -
0"
0#
0%
0&
1)
0+
#201
1!
b1z111 -
1"
1$
#202
0!
b0z111 -
0"
1#
#203
1!
b1z111 -
1"
1(
#204
0!
b0z111 -
0"
0#
0$
1%
0'
#205
1!
b1z111 -
1"
1&
#206
0!
b0z111 -
0"
1#
#207
1!
b10000z110 -
1"
1$
1*
#208
0"
0#
0%
0)
#209
0!
b0z010 -
1"
1,
#210
0!
b0z000 -
0"
1#
0$
0&
1'
0(
1+
#211
1"
#212
0"
0#
1%
#213
1"
1$
#214
0"
1#
#215
1"
1&
#216
b0z001 -
0"
0#
0$
0%
0'
1)
0*
#217
1"
1(
#218
0"
1#
#219
1"
1$
#220
b0z111 -
0"
0#
1%
0&
0+
0,
#221
1!
b1z111 -
1"
#222
0!
b0z111 -
0"
1#
0$
1'
#223
1!
b1z111 -
1"
#224
0!
b0z111 -
0"
0#
0%
0(
0)
#225
1!
b10000z110 -
1"
1$
1&
1*
#226
0"
1#
#227
1"
#228
0"
0#
0$
1%
0'
#229
1"
#230
0!
b0z100 -
0"
1#
0&
1+
#231
0!
b0z000 -
1"
1$
1(
1,
#232
1!
b10000000z000 -
0"
0#
0%
1)
#233
1"
#234
0!
b0z001 -
0"
1#
0$
1'
0*
#235
1"
1&
#236
1!
b1000z001 -
0"
0#
1%
#237
1"
1$
#238
0"
1#
0(
#239
1"
#240
0!
b0z011 -
0"
0#
0$
0%
0&
0'
0)
0+
#241
1"
#242
b0z111 -
0"
1#
0,
#243
0!
b0z110 -
1"
1$
1*
#244
0"
0#
1%
#245
1!
b10000z110 -
1"
1&
1(
#246
0"
1#
0$
1'
#247
1"
#248
0"
0#
0%
1)
#249
1"
1$
#250
b1000000z100 -
0"
1#
0&
1+
#251
1"
#252
0!
b0z101 -
0"
0#
0$
1%
0'
0(
0*
#253
1!
b1000z001 -
1"
1,
#254
0"
1#
#255
1"
1$
1&
#256
0!
b0z001 -
0"
0#
0%
0)
#257
1"
#258
0"
1#
0$
1'
#259
1"
1(
#260
b0z011 -
0"
0#
1%
0&
0+
#261
1!
b100000z010 -
1"
1$
1*
#262
0"
1#
#263
1"
#264
0!
b0z110 -
0"
0#
0$
0%
0'
1)
0,
#265
1!
b10000z110 -
1"
1&
#266
0"
1#
0(
#267
1"
1$
#268
0"
0#
1%
#269
1"
#270
0!
b0z101 -
0"
1#
0$
0&
1'
0*
1+
#271
1"
#272
0"
0#
0%
0)
#273
1!
b100z101 -
1"
1$
1(
#274
0"
1#
#275
0!
b0z001 -
1"
1&
1,
#276
1!
b1000z001 -
0"
0#
0$
1%
0'
#277
1"
#278
0"
1#
#279
0!
b0z000 -
1"
1$
1*
#280
b0z010 -
0"
0#
0%
0&
0(
1)
0+
#281
1"
#282
1!
b100000z010 -
0"
1#
0$
1'
#283
1"
#284
0"
0#
1%
#285
1"
1$
1&
#286
1!
b10000z110 -
0"
1#
0,
#287
1"
1(
#288
0!
b0z111 -
0"
0#
0$
0%
0'
0)
0*
#289
1!
b1z111 -
1"
#290
0!
b0z101 -
0"
1#
0&
1+
#291
1!
b100z101 -
1"
1$
#292
0"
0#
1%
#293
1"
#294
0!
b0z101 -
0"
1#
0$
1'
0(
#295
1"
1&
#296
0"
0#
0%
1)
#297
1!
b10000000z000 -
1"
1$
1*
1,
#298
0"
1#
#299
1"
#300
0!
b0z010 -
0"
0#
0$
1%
0&
0'
0+
#301
1"
1(
#302
0"
1#
#303
1"
1$
#304
0"
0#
0%
0)
#305
1"
1&
#306
1!
b10z011 -
0"
1#
0$
1'
0*
#307
1"
#308
0!
b0z111 -
0"
0#
1%
0(
0,
#309
1!
b1z111 -
1"
1$
#310
b100z101 -
0"
1#
0&
1+
#311
1"
#312
0!
b0z101 -
0"
0#
0$
0%
0'
1)
#313
1"
#314
0"
1#
#315
1!
b1000000z100 -
1"
1$
1&
1(
1*
#316
0"
0#
1%
#317
1"
#318
0"
1#
0$
1'
#319
b10000000z000 -
1"
1,
#320
1!
b100000z010 -
0"
0#
0%
0&
0)
0+
#321
1"
1$
#322
0"
1#
0(
#323
1"
#324
0!
b0z011 -
0"
0#
0$
1%
0'
0*
#325
1"
1&
#326
1!
b10z011 -
0"
1#
#327
1"
1$
#328
0!
b0z011 -
0"
0#
0%
1)
#329
1"
1(
#330
b0z101 -
0"
1#
0$
0&
1'
1+
0,
#331
1"
#332
0"
0#
1%
#333
1!
b1000000z100 -
1"
1$
1*
#334
0"
1#
#335
1"
1&
#336
0!
b0z100 -
0"
0#
0$
0%
0'
0(
0)
#337
1"
#338
0"
1#
#339
1"
1$
#340
b0z110 -
0"
0#
1%
0&
0+
#341
b0z010 -
1"
1,
#342
1!
b10z011 -
0"
1#
0$
1'
0*
#343
1"
1(
#344
0!
b0z011 -
0"
0#
0%
1)
#345
1"
1$
1&
#346
1!
b10z011 -
0"
1#
#347
1"
#348
0!
b0z011 -
0"
0#
0$
1%
0'
#349
1"
#350
1!
b1000z001 -
0"
1#
0&
0(
1+
#351
b10000000z000 -
1"
1$
1*
#352
0!
b0z100 -
0"
0#
0%
0)
0,
#353
1"
#354
0"
1#
0$
1'
#355
1"
1&
#356
0"
0#
1%
#357
1!
b1000000z100 -
1"
1$
1(
#358
0"
1#
#359
1"
#360
0!
b0z111 -
0"
0#
0$
0%
0&
0'
1)
0*
0+
#361
1!
b1z111 -
1"
#362
0!
b0z111 -
0"
1#
#363
1!
b10z011 -
1"
1$
1,
#364
0!
b0z011 -
0"
0#
1%
0(
#365
1"
1&
#366
1!
b10z011 -
0"
1#
0$
1'
#367
1"
#368
0!
b0z011 -
0"
0#
0%
0)
#369
1!
b100000z010 -
1"
1$
1*
#370
0!
b0z000 -
0"
1#
0&
1+
#371
1"
1(
#372
0"
0#
0$
1%
0'
#373
1"
#374
1!
b1000000z100 -
0"
1#
0,
#375
1"
1$
1&
#376
0"
0#
0%
1)
#377
1"
#378
0!
b0z101 -
0"
1#
0$
1'
0(
0*
#379
1"
#380
b0z111 -
0"
0#
1%
0&
0+
#381
1!
b1z111 -
1"
1$
#382
0!
b0z111 -
0"
1#
#383
1!
b1z111 -
1"
#384
0!
b0z111 -
0"
0#
0$
0%
0'
0)
#385
0!
b0z011 -
1"
1&
1(
1,
#386
1!
b10z011 -
0"
1#
#387
0!
b0z010 -
1"
1$
1*
#388
0"
0#
1%
#389
1"
#390
0!
b0z000 -
0"
1#
0$
0&
1'
1+
#391
1"
#392
1!
b10000000z000 -
0"
0#
0%
0(
1)
#393
1"
1$
#394
0"
1#
#395
1"
1&
#396
0!
b0z101 -
0"
0#
0$
1%
0'
0*
0,
#397
1"
#398
0"
1#
#399
1!
b100z101 -
1"
1$
1(
#400
0!
b0z111 -
0"
0#
0%
0&
0)
0+
#401
1!
b1z111 -
1"
#402
0!
b0z111 -
0"
1#
0$
1'
#403
1!
b1z111 -
1"
#404
0!
b0z111 -
0"
0#
1%
#405
1!
b10000z110 -
1"
1$
1&
1*
#406
0"
1#
0(
#407
b100000z010 -
1"
1,
#408
0!
b0z010 -
0"
0#
0$
0%
0'
1)
#409
1"
#410
1!
b10000000z000 -
0"
1#
0&
1+
#411
1"
1$
#412
0"
0#
1%
#413
1"
1(
#414
1!
b1000z001 -
0"
1#
0$
1'
0*
#415
1"
1&
#416
0!
b0z001 -
0"
0#
0%
0)
#417
1"
1$
#418
1!
b100z101 -
0"
1#
0,
#419
1"
#420
0!
b0z111 -
0"
0#
0$
1%
0&
0'
0(
0+
#421
1!
b1z111 -
1"
#422
0!
b0z111 -
0"
1#
#423
0!
b0z110 -
1"
1$
1*
#424
0"
0#
0%
1)
#425
1!
b10000z110 -
1"
1&
#426
0"
1#
0$
1'
#427
1"
1(
#428
0"
0#
1%
#429
b100000z010 -
1"
1$
1,
#430
b10000000z000 -
0"
1#
0&
1+
#431
1"
#432
0!
b0z001 -
0"
0#
0$
0%
0'
0)
0*
#433
1"
#434
0"
1#
0(
#435
1"
1$
1&
#436
1!
b1000z001 -
0"
0#
1%
#437
1"
#438
0"
1#
0$
1'
#439
1"
#440
0!
b0z111 -
0"
0#
0%
0&
1)
0+
0,
#441
0!
b0z110 -
1"
1$
1(
1*
#442
0"
1#
#443
1"
#444
0"
0#
0$
1%
0'
#445
1!
b10000z110 -
1"
1&
#446
0"
1#
#447
1"
1$
#448
0"
0#
0%
0(
0)
#449
1"
#450
0!
b0z101 -
0"
1#
0$
0&
1'
0*
1+
#451
b0z001 -
1"
1,
#452
1!
b1000z001 -
0"
0#
1%
#453
1"
1$
#454
0"
1#
#455
1"
1&
1(
#456
0!
b0z001 -
0"
0#
0$
0%
0'
1)
#457
1"
#458
0"
1#
#459
1!
b10000000z000 -
1"
1$
1*
#460
0!
b0z010 -
0"
0#
1%
0&
0+
#461
1"
#462
b0z110 -
0"
1#
0$
1'
0(
0,
#463
1"
#464
0"
0#
0%
0)
#465
1!
b10000z110 -
1"
1$
1&
#466
0"
1#
#467
1"
#468
0!
b0z111 -
0"
0#
0$
1%
0'
0*
#469
1!
b1z111 -
1"
1(
#470
0!
b0z101 -
0"
1#
0&
1+
#471
1!
b100z101 -
1"
1$
#472
0"
0#
0%
1)
#473
0!
b0z001 -
1"
1,
#474
0"
1#
0$
1'
#475
1"
1&
#476
1!
b1000z001 -
0"
0#
1%
0(
#477
b10000000z000 -
1"
1$
1*
#478
0"
1#
#479
1"
#480
0!
b0z010 -
0"
0#
0$
0%
0&
0'
0)
0+
#481
1"
#482
0"
1#
#483
1"
1$
1(
#484
b0z110 -
0"
0#
1%
0,
#485
1!
b10000z110 -
1"
1&
#486
0!
b0z111 -
0"
1#
0$
1'
0*
#487
1!
b1z111 -
1"
#488
0!
b0z111 -
0"
0#
0%
1)
#489
1!
b1z111 -
1"
1$
#490
b100z101 -
0"
1#
0&
0(
1+
#491
1"
#492
0!
b0z101 -
0"
0#
0$
1%
0'
#493
1"
#494
0"
1#
#495
1!
b10000000z000 -
1"
1$
1&
1*
1,
#496
0!
b0z000 -
0"
0#
0%
0)
#497
1"
1(
#498
0"
1#
0$
1'
#499
1"
#500
1!
b100000z010 -
0"
0#
1%
0&
0+
