behavioural_modelling/fulladdr.v
module fulladdr(output reg s, output reg c, input wire a,b,cin);
always @ (a or b or cin) begin
    s = a ^ b ^ cin;
    c = (a&b) | (a^b) & cin;
/*case (a|b|cin)
    3'b000: begin s=0; c=0; end
    3'b001: begin s=1; c=0; end
    3'b010: begin s=1; c=0; end
    3'b011: begin s=0; c=1; end
    3'b100: begin s=1; c=0; end
    3'b101: begin s=0; c=1; end
    3'b110: begin s=0; c=1; end
    3'b111: begin s=1; c=1; end
endcase */ 
end
endmodule;

behavioural_modelling/fulladdr_tb.v
`timescale 1ns/1ns
`include "fulladdr.v"
module fulladdr_tb;
reg a,b,cin;
wire s,c;
fulladdr uut (s,c,a,b,cin);
initial begin
    $dumpfile("fulladdr_tb.vcd");
    $dumpvars();
    {a,b,cin} = 3'd0; #10
    {a,b,cin} = 3'd1; #10
    {a,b,cin} = 3'd2; #10
    {a,b,cin} = 3'd3; #10
    {a,b,cin} = 3'd4; #10 
    {a,b,cin} = 3'd5; #10
    {a,b,cin} = 3'd6; #10
    {a,b,cin} = 3'd7; #10
    $display("This is complete");
end
endmodule

behavioural_modelling/fulladdr_tb.vcd
$date
	Mon Jan 24 20:22:09 2022
$end
$version
	Icarus Verilog
$end
$timescale
	1ns
$end
$scope module fulladdr_tb $end
$var wire 1 ! s $end
$var wire 1 " c $end
$var reg 1 # a $end
$var reg 1 $ b $end
$var reg 1 % cin $end
$scope module uut $end
$var wire 1 # a $end
$var wire 1 $ b $end
$var wire 1 % cin $end
$var reg 1 " c $end
$var reg 1 ! s $end
$upscope $end
$upscope $end
$enddefinitions $end
#0
$dumpvars
0%
0$
0#
0"
0!
$end
#10
1!
1%
#20
1$
0%
#30
1"
0!
1%
#40
0"
1!
1#
0$
0%
#50
1"
0!
1%
#60
1$
0%
#70
1!
1%
