behavioural_modelling/fullsub.v
module fullsub(input x,y,z, output reg b,d);
always @ (x or y or z) begin
//    b = ~x&(y^z) | (y&z);
//    d = x^y^z;
if (x==0 && y==0 && z==0) begin
    d=0;
    b=0;
end

else if (x==0 && y==0 && z==1) begin
    d=1;
    b=1;
end

else if (x==0 && y==1 && z==0) begin
    d=1;
    b=1;
end

else if (x==0 && y==1 && z==1) begin
    d=1;
    b=1;
end

else if (x==1 && y==0 && z==0) begin
    d=1;
    b=0;
end

else if (x==1 && y==0 && z==1) begin
    d=0;
    b=0;
end

else if (x==1 && y==1 && z==0) begin
    d=0;
    b=0;
end

else if (x==1 && y==1 && z==1) begin
    d=1;
    b=1;
end

end
endmodule

behavioural_modelling/fullsub_tb.v
`timescale 1ns/1ns
`include "fullsub.v"
module fullsub_tb;
reg x,y,z;
wire b,d;
fullsub uut(x,y,z,b,d);
initial begin
    $dumpfile("fullsub_tb.vcd");
    $dumpvars();
    x=0;y=0;z=0;
    #100 $finish;
end

always #40 x=~x;
always #20 y=~y;
always #10 z=~z;

endmodule

behavioural_modelling/fullsub_tb.vcd
$date
	Tue Jan 25 21:26:10 2022
$end
$version
	Icarus Verilog
$end
$timescale
	1ns
$end
$scope module fullsub_tb $end
$var wire 1 ! d $end
$var wire 1 " b $end
$var reg 1 # x $end
$var reg 1 $ y $end
$var reg 1 % z $end
$scope module uut $end
$var wire 1 # x $end
$var wire 1 $ y $end
$var wire 1 % z $end
$var reg 1 " b $end
$var reg 1 ! d $end
$upscope $end
$upscope $end
$enddefinitions $end
#0
$dumpvars
0%
0$
0#
0"
0!
$end
#10
1"
1!
1%
#20
0%
1$
#30
1%
#40
0"
0%
0$
1#
#50
0!
1%
#60
0%
1$
#70
1"
1!
1%
#80
0"
0!
0%
0$
0#
#90
1"
1!
1%
#100
0%
1$
