behavioural_modelling/mux2.v
module mux2(input wire a,b,s, output reg y);
always @ (a|b|s) begin
    if (s) 
        y=b;
    else
        y=a;
end
endmodule

behavioural_modelling/mux2_tb.v
`timescale 1ns / 1ns
`include "mux2.v"
module mux2_tb;
reg a,b,s;
wire y;
mux2 uut (a,b,s,y);
initial begin
    $dumpfile("mux2_tb.vcd");
    $dumpvars(0, mux2_tb);
    {a,b,s} = 3'd0; #10;
    {a,b,s} = 3'd1; #10;
    {a,b,s} = 3'd2; #10;
    {a,b,s} = 3'd3; #10;
    {a,b,s} = 3'd4; #10;
    {a,b,s} = 3'd5; #10;
    {a,b,s} = 3'd6; #10;
    {a,b,s} = 3'd7; #10;
end

endmodule

behavioural_modelling/mux2_tb.vcd
$date
	Tue Jan 25 22:10:04 2022
$end
$version
	Icarus Verilog
$end
$timescale
	1ns
$end
$scope module mux2_tb $end
$var wire 1 ! y $end
$var reg 1 " a $end
$var reg 1 # b $end
$var reg 1 $ s $end
$scope module uut $end
$var wire 1 " a $end
$var wire 1 # b $end
$var wire 1 $ s $end
$var reg 1 ! y $end
$upscope $end
$upscope $end
$enddefinitions $end
#0
$dumpvars
0$
0#
0"
0!
$end
#10
1$
#20
1#
0$
#30
1$
#40
1"
0#
0$
#50
1$
#60
1#
0$
#70
1$
