behavioural_modelling/srff.v
module srff(input s,r,clk,clear, output reg q, output reg qbar);
always @ (posedge clk) begin
    if(clear) begin
        q<=0; qbar<=1;
    end
    else if (s==0 && r==1) begin
        q<=0; qbar<=1;
    end
    else if (s==1 && r==0) begin
        q<=1; qbar<=0;
    end
    
end
endmodule

behavioural_modelling/srff_tb.v
`timescale 1ns/1ns
`include "srff.v"

module srff_tb;
reg s,r,clk,clear;
wire q, qbar;
srff uut(s,r,clk,clear,q,qbar);

initial begin
    $dumpfile ("srff_tb.vcd");
    $dumpvars(1);
    clear=0; clk=0; s=0; r=0;
    #500 $finish;
end
always #100 clear = ~clear;
always #80 s=~s;
always #40 r=~r;
always #5 clk=~clk;
endmodule

behavioural_modelling/srff_tb.vcd
$date
	Thu Jan 27 20:37:00 2022
$end
$version
	Icarus Verilog
$end
$timescale
	1ns
$end
$scope module srff_tb $end
$var wire 1 ! qbar $end
$var wire 1 " q $end
$var reg 1 # clear $end
$var reg 1 $ clk $end
$var reg 1 % r $end
$var reg 1 & s $end
$upscope $end
$enddefinitions $end
#0
$dumpvars
0&
0%
0$
0#
x"
x!
$end
#5
1$
#10
0$
#15
1$
#20
0$
#25
1$
#30
0$
#35
1$
#40
0$
1%
#45
1!
0"
1$
#50
0$
#55
1$
#60
0$
#65
1$
#70
0$
#75
1$
#80
0$
0%
1&
#85
0!
1"
1$
#90
0$
#95
1$
#100
0$
1#
#105
1!
0"
1$
#110
0$
#115
1$
#120
0$
1%
#125
1$
#130
0$
#135
1$
#140
0$
#145
1$
#150
0$
#155
1$
#160
0$
0%
0&
#165
1$
#170
0$
#175
1$
#180
0$
#185
1$
#190
0$
#195
1$
#200
0$
1%
0#
#205
1$
#210
0$
#215
1$
#220
0$
#225
1$
#230
0$
#235
1$
#240
0$
0%
1&
#245
0!
1"
1$
#250
0$
#255
1$
#260
0$
#265
1$
#270
0$
#275
1$
#280
0$
1%
#285
1$
#290
0$
#295
1$
#300
0$
1#
#305
1!
0"
1$
#310
0$
#315
1$
#320
0$
0%
0&
#325
1$
#330
0$
#335
1$
#340
0$
#345
1$
#350
0$
#355
1$
#360
0$
1%
#365
1$
#370
0$
#375
1$
#380
0$
#385
1$
#390
0$
#395
1$
#400
0$
0%
1&
0#
#405
0!
1"
1$
#410
0$
#415
1$
#420
0$
#425
1$
#430
0$
#435
1$
#440
0$
1%
#445
1$
#450
0$
#455
1$
#460
0$
#465
1$
#470
0$
#475
1$
#480
0$
0%
0&
#485
1$
#490
0$
#495
1$
#500
0$
1#
